Workbook

Sheet 2-4_PL①Input
B2: 2-4. PLシミュレーション ①Input（前提・青字が入力）
D4: 青字のセルだけを変更すれば、②計算・③Outputが自動で更新されます。
D5: 【売上ドライバー】
D7: 項目 | E7: 値 | F7: 単位
D8: 客室数 | E8: 20 | F8: 室
D9: 営業日数 | E9: 365 | F9: 日
D10: 稼働率 | E10: 0.65
D11: ADR（客室単価） | E11: 50000 | F11: 円
D12: 宿泊人数/室 | E12: 2 | F12: 人
D13: 飲食単価/人 | E13: 6000 | F13: 円
D17: 【コストドライバー】
D19: 項目 | E19: 値 | F19: 単位
D20: 変動費率（対売上） | E20: 0.3
D21: 人件費（固定・年） | E21: 60000000 | F21: 円
D22: その他固定費（年） | E22: 48000000 | F22: 円
D24: ※ 青字＝手入力の前提。黒字＝数式。緑字＝他シート参照（②③で使用）。

Sheet 2-4_PL②計算
B2: 2-4. PLシミュレーション ②計算（Inputを参照して積み上げ）
D4: 重要！：原則、青字、緑字、黒字を1セルにごっちゃにして計算しない。
D5: 客室・飲食売上の積み上げ
D7: 項目 | E7: 金額(円) | F7: 計算の内容
D8: 客室数 | E8: ='2-4_PL①Input'!E8 | F8: Inputシートより
D9: 営業日数 | E9: ='2-4_PL①Input'!E9 | F9: Inputシートより
D10: 稼働率 | E10: ='2-4_PL①Input'!E10 | F10: Inputシートより
D11: 稼働室数（室・年） | E11: =E8*E9*E10 | F11: 客室数×営業日数×稼働率
D13: ='2-4_PL①Input'!$D$11 | E13: ='2-4_PL①Input'!E11 | F13: Inputシートより
D14: 客室売上 | E14: =E11*E13 | F14: 販売室数×ADR
D16: 宿泊人数/室 | E16: ='2-4_PL①Input'!E12 | F16: Inputシートより
D17: ='2-4_PL①Input'!$D$13 | E17: ='2-4_PL①Input'!E13 | F17: Inputシートより
D18: 飲食売上 | E18: =E11*E16*E17 | F18: 稼働室数x宿泊人数/室×飲食単価/人
D20: 売上高 計 | E20: =E14+E18 | F20: 客室売上＋飲食売上
D22: 変動費率 | E22: ='2-4_PL①Input'!E20 | F22: Inputシートより
D23: 変動費 | E23: =E20*E22 | F23: 売上高×変動費率
D24: 限界利益 | E24: =E20-E23 | F24: 売上高−変動費
D26: ='2-4_PL①Input'!D21 | E26: ='2-4_PL①Input'!E21
D27: ='2-4_PL①Input'!D22 | E27: ='2-4_PL①Input'!E22
D28: 固定費 計 | E28: =SUM(E26:E27) | F28: 人件費＋その他固定費
D30: 営業利益 | E30: =E24-E28 | F30: 限界利益−固定費
D32: 緑字＝①Inputへの参照。黄色＝主要な中間・最終アウトプット。

Sheet 2-4_PL③Output
B2: 2-4. PLシミュレーション ③Output（PLサマリ）
D4: PPTに張り付けるサマリなどは、数字の色を付けません。
D5: 年間 損益計算書（サマリ）
D6: 単位： 百万円
D8: 項目 | E8: 金額 | F8: 対売上%
D9: 売上高 | E9: ='2-4_PL②計算'!E20/10^6 | F9: =E9/$E$9
D11: 変動費 | E11: ='2-4_PL②計算'!E23/10^6 | F11: =-E11/$E$9
D12: 限界利益 | E12: =E9-E11 | F12: =E12/$E$9
D14: 固定費 | E14: ='2-4_PL②計算'!E28/10^6 | F14: =-E14/$E$9
D15: 営業利益 | E15: =E12-E14 | F15: =E15/$E$9
D17: Input①の青字（稼働率・ADR等）を変えると、この③まで一気に更新されます。
